# Final Enum Conversion Plan

**Date**: 2025-11-18
**Status**: Planning Phase
**Objective**: Convert the last 3 remaining plain enums to type-safe enum classes

---

## Executive Summary

After analyzing the codebase, **3 plain enums remain** to be converted to enum class:

1. **KOption** - Pack/unpack format options (11 values, ~23 usages, 2 files)
2. **expkind** - Expression descriptor kinds (21 values, ~29 usages, 8 files)
3. **OpCode** - VM bytecode instructions (83 values, ~70 usages, 12 files)

**Recommended Order**: KOption → expkind → OpCode (lowest to highest risk)

**Estimated Total Time**: 6-8 hours
**Performance Target**: ≤4.33s (≤3% regression from 4.20s baseline)

---

## Recent Enum Conversion History

**Completed enum class conversions**:
- ✅ Phase 100: RESERVED enum (150+ conversions, 4 files)
- ✅ Phase 99: TMS enum (tag methods)
- ✅ Phase 98: OpMode enum (6 values)
- ✅ Phase 97: F2Imod enum (float-to-int modes)
- ✅ Phase 96: BinOpr and UnOpr enums (binary/unary operators)

**Pattern established**: Convert definition to `enum class`, then update all usages with `static_cast<int>(EnumClass::VALUE)` or `EnumClass::VALUE` as appropriate.

---

## Enum #1: KOption (Pack/Unpack Format Options)

### Overview

**Location**: `src/libraries/lstrlib.cpp:1430-1442`
**Scope**: Local to string library pack/unpack implementation
**Risk Level**: ⭐ **LOW** (isolated, single-file usage)

**Current Definition**:
```cpp
typedef enum KOption {
  Kint,      /* signed integers */
  Kuint,     /* unsigned integers */
  Kfloat,    /* single-precision floating-point numbers */
  Knumber,   /* Lua "native" floating-point numbers */
  Kdouble,   /* double-precision floating-point numbers */
  Kchar,     /* fixed-length strings */
  Kstring,   /* strings with prefixed length */
  Kzstr,     /* zero-terminated strings */
  Kpadding,  /* padding */
  Kpaddalign,/* padding for alignment */
  Knop       /* no-op (configuration or spaces) */
} KOption;
```

### Usage Analysis

**Files Affected**: 2 files
- `src/libraries/lstrlib.cpp` (main usage, ~20 sites)
- `tags` (symbol table, no code changes needed)

**Conversion Sites** (~20 locations):
- Function parameters: `KOption opt`
- Variable declarations: `KOption opt;`
- Switch statements: `switch (opt)`
- Case labels: `case Kint:`, `case Kuint:`, etc.
- Assignments: `opt = Kint;`

### Conversion Strategy

**Target Definition**:
```cpp
enum class KOption {
  Kint,      /* signed integers */
  Kuint,     /* unsigned integers */
  Kfloat,    /* single-precision floating-point numbers */
  Knumber,   /* Lua "native" floating-point numbers */
  Kdouble,   /* double-precision floating-point numbers */
  Kchar,     /* fixed-length strings */
  Kstring,   /* strings with prefixed length */
  Kzstr,     /* zero-terminated strings */
  Kpadding,  /* padding */
  Kpaddalign,/* padding for alignment */
  Knop       /* no-op (configuration or spaces) */
};
```

**Required Changes**:
1. Convert `typedef enum KOption { ... } KOption;` → `enum class KOption { ... };`
2. Update all case labels: `case Kint:` → `case KOption::Kint:`
3. Update all assignments: `opt = Kint;` → `opt = KOption::Kint;`
4. Keep function parameters as-is: `KOption opt` (no change needed)

**Estimated Time**: 1 hour
**Risk Assessment**: **VERY LOW** - Fully isolated within string library

---

## Enum #2: expkind (Expression Descriptor Kinds)

### Overview

**Location**: `src/compiler/lparser.h:28-70`
**Scope**: Compiler expression analysis
**Risk Level**: ⭐⭐ **MEDIUM** (compiler-only, no runtime impact)

**Current Definition**:
```cpp
typedef enum {
  VVOID,     /* empty expression list */
  VNIL,      /* constant nil */
  VTRUE,     /* constant true */
  VFALSE,    /* constant false */
  VK,        /* constant in 'k' */
  VKFLT,     /* floating constant */
  VKINT,     /* integer constant */
  VKSTR,     /* string constant */
  VNONRELOC, /* fixed register */
  VLOCAL,    /* local variable */
  VGLOBAL,   /* global variable */
  VUPVAL,    /* upvalue variable */
  VCONST,    /* compile-time constant */
  VINDEXED,  /* indexed variable */
  VINDEXUP,  /* indexed upvalue */
  VINDEXI,   /* indexed with constant integer */
  VINDEXSTR, /* indexed with literal string */
  VJMP,      /* test/comparison */
  VRELOC,    /* result in any register */
  VCALL,     /* function call */
  VVARARG    /* vararg expression */
} expkind;
```

### Usage Analysis

**Files Affected**: 8 files (all compiler-related)
- `src/compiler/lparser.h` (definition + ~7 references)
- `src/compiler/parser.cpp` (main usage, estimated ~15 sites)
- `src/compiler/parseutils.cpp` (estimated ~5 sites)
- `src/compiler/funcstate.cpp` (estimated ~2 sites)
- Documentation/tags files (no code changes)

**Conversion Sites** (~25-30 locations):
- Field in `expdesc` class: `expkind k;` → Keep as-is
- Function parameters: Rare, mostly field access
- Comparisons: `e->k == VLOCAL` → `e->k == expkind::VLOCAL`
- Switch statements: `switch (e->k)` → No change
- Case labels: `case VLOCAL:` → `case expkind::VLOCAL:`
- Assignments: `e->k = VLOCAL;` → `e->k = expkind::VLOCAL;`

### Conversion Strategy

**Target Definition**:
```cpp
/* kinds of variables/expressions */
enum class expkind {
  VVOID,     /* empty expression list */
  VNIL,      /* constant nil */
  VTRUE,     /* constant true */
  VFALSE,    /* constant false */
  VK,        /* constant in 'k' */
  VKFLT,     /* floating constant */
  VKINT,     /* integer constant */
  VKSTR,     /* string constant */
  VNONRELOC, /* fixed register */
  VLOCAL,    /* local variable */
  VGLOBAL,   /* global variable */
  VUPVAL,    /* upvalue variable */
  VCONST,    /* compile-time constant */
  VINDEXED,  /* indexed variable */
  VINDEXUP,  /* indexed upvalue */
  VINDEXI,   /* indexed with constant integer */
  VINDEXSTR, /* indexed with literal string */
  VJMP,      /* test/comparison */
  VRELOC,    /* result in any register */
  VCALL,     /* function call */
  VVARARG    /* vararg expression */
};
```

**Required Changes**:
1. Convert `typedef enum { ... } expkind;` → `enum class expkind { ... };`
2. Update field in `expdesc`: `expkind k;` (no change)
3. Update all comparisons: `e->k == VLOCAL` → `e->k == expkind::VLOCAL`
4. Update all case labels: `case VLOCAL:` → `case expkind::VLOCAL:`
5. Update all assignments: `e->k = VLOCAL;` → `e->k = expkind::VLOCAL;`
6. Check static helper methods in expdesc class (may need updates)

**Estimated Time**: 2-3 hours
**Risk Assessment**: **LOW-MEDIUM** - Compile-time only, no VM impact

---

## Enum #3: OpCode (VM Bytecode Instructions)

### Overview

**Location**: `src/compiler/lopcodes.h:358-471`
**Scope**: VM instruction set (83 opcodes)
**Risk Level**: ⭐⭐⭐ **HIGH** (VM critical, hot path)

**Current Definition**:
```cpp
typedef enum {
  OP_MOVE, OP_LOADI, OP_LOADF, OP_LOADK, OP_LOADKX,
  OP_LOADFALSE, OP_LFALSESKIP, OP_LOADTRUE, OP_LOADNIL,
  OP_GETUPVAL, OP_SETUPVAL,
  OP_GETTABUP, OP_GETTABLE, OP_GETI, OP_GETFIELD,
  OP_SETTABUP, OP_SETTABLE, OP_SETI, OP_SETFIELD,
  OP_NEWTABLE, OP_SELF,
  OP_ADDI, OP_ADDK, OP_SUBK, OP_MULK, OP_MODK,
  OP_POWK, OP_DIVK, OP_IDIVK,
  OP_BANDK, OP_BORK, OP_BXORK,
  OP_SHLI, OP_SHRI,
  OP_ADD, OP_SUB, OP_MUL, OP_MOD, OP_POW, OP_DIV, OP_IDIV,
  OP_BAND, OP_BOR, OP_BXOR, OP_SHL, OP_SHR,
  OP_MMBIN, OP_MMBINI, OP_MMBINK,
  OP_UNM, OP_BNOT, OP_NOT, OP_LEN,
  OP_CONCAT, OP_CLOSE, OP_TBC, OP_JMP,
  OP_EQ, OP_LT, OP_LE,
  OP_EQK, OP_EQI, OP_LTI, OP_LEI, OP_GTI, OP_GEI,
  OP_TEST, OP_TESTSET,
  OP_CALL, OP_TAILCALL,
  OP_RETURN, OP_RETURN0, OP_RETURN1,
  OP_FORLOOP, OP_FORPREP,
  OP_TFORPREP, OP_TFORCALL, OP_TFORLOOP,
  OP_SETLIST, OP_CLOSURE, OP_VARARG, OP_VARARGPREP,
  OP_EXTRAARG
} OpCode;
```

### Usage Analysis

**Files Affected**: 12 files
- `src/compiler/lopcodes.h` (definition + utilities, ~10 references)
- `src/compiler/lopcodes.cpp` (~5 references)
- `src/compiler/lcode.cpp` (heavy usage, ~30+ references)
- `src/compiler/parser.cpp` (~5 references)
- `src/vm/lvm.cpp` (VM interpreter, critical path, ~10 references)
- `src/core/ldebug.cpp` (~5 references)
- `src/testing/ltests.cpp` (testing only)
- Documentation/tags files

**Critical Usage Patterns**:

1. **Switch dispatch in VM** (`lvm.cpp`):
   ```cpp
   switch (GET_OPCODE(i)) {
     case OP_MOVE: ...
     case OP_LOADI: ...
     // 83 cases total
   }
   ```

2. **Code generation** (`lcode.cpp`):
   ```cpp
   void codeABC(OpCode o, int a, int b, int c);
   Instruction CREATE_ABCk(OpCode o, int a, int b, int c, int k);
   ```

3. **Instruction queries**:
   ```cpp
   OpCode GET_OPCODE(Instruction i);
   OpMode getOpMode(OpCode m);
   ```

4. **Constant expression**: `NUM_OPCODES = ((int)(OP_EXTRAARG) + 1)`

### Conversion Strategy

**Target Definition**:
```cpp
enum class OpCode {
  OP_MOVE, OP_LOADI, OP_LOADF, OP_LOADK, OP_LOADKX,
  OP_LOADFALSE, OP_LFALSESKIP, OP_LOADTRUE, OP_LOADNIL,
  OP_GETUPVAL, OP_SETUPVAL,
  OP_GETTABUP, OP_GETTABLE, OP_GETI, OP_GETFIELD,
  OP_SETTABUP, OP_SETTABLE, OP_SETI, OP_SETFIELD,
  OP_NEWTABLE, OP_SELF,
  OP_ADDI, OP_ADDK, OP_SUBK, OP_MULK, OP_MODK,
  OP_POWK, OP_DIVK, OP_IDIVK,
  OP_BANDK, OP_BORK, OP_BXORK,
  OP_SHLI, OP_SHRI,
  OP_ADD, OP_SUB, OP_MUL, OP_MOD, OP_POW, OP_DIV, OP_IDIV,
  OP_BAND, OP_BOR, OP_BXOR, OP_SHL, OP_SHR,
  OP_MMBIN, OP_MMBINI, OP_MMBINK,
  OP_UNM, OP_BNOT, OP_NOT, OP_LEN,
  OP_CONCAT, OP_CLOSE, OP_TBC, OP_JMP,
  OP_EQ, OP_LT, OP_LE,
  OP_EQK, OP_EQI, OP_LTI, OP_LEI, OP_GTI, OP_GEI,
  OP_TEST, OP_TESTSET,
  OP_CALL, OP_TAILCALL,
  OP_RETURN, OP_RETURN0, OP_RETURN1,
  OP_FORLOOP, OP_FORPREP,
  OP_TFORPREP, OP_TFORCALL, OP_TFORLOOP,
  OP_SETLIST, OP_CLOSURE, OP_VARARG, OP_VARARGPREP,
  OP_EXTRAARG
};
```

**Required Changes**:

1. **Definition** (`lopcodes.h`):
   - Convert `typedef enum { ... } OpCode;` → `enum class OpCode { ... };`
   - Update `NUM_OPCODES`: `static_cast<int>(OpCode::OP_EXTRAARG) + 1`

2. **VM switch dispatch** (`lvm.cpp`):
   - Keep: `switch (GET_OPCODE(i))` (returns OpCode)
   - Update 83 case labels: `case OP_MOVE:` → `case OpCode::OP_MOVE:`

3. **Code generation** (`lcode.cpp`):
   - Keep function signatures: `void codeABC(OpCode o, ...)` (no change)
   - Update calls passing literals: `codeABC(OP_MOVE, ...)` → `codeABC(OpCode::OP_MOVE, ...)`
   - Update array/table indexing with cast: `opmode[static_cast<int>(op)]`

4. **Instruction macros** (`lopcodes.h`):
   - Functions returning OpCode: No cast needed
   - Functions taking OpCode for indexing: Add cast to int
   - Example: `getOpMode(static_cast<int>(op))`

5. **Parser/Debug** (`parser.cpp`, `ldebug.cpp`):
   - Update case labels in switches
   - Update comparisons: `op == OP_MOVE` → `op == OpCode::OP_MOVE`

**Special Considerations**:

⚠️ **Performance Critical**: VM interpreter hot path affected
⚠️ **Extensive Testing Required**: 83 opcodes, must verify all paths
⚠️ **Benchmark Mandatory**: Must meet ≤4.33s target after conversion

**Estimated Time**: 3-4 hours
**Risk Assessment**: **MEDIUM-HIGH** - VM critical, requires careful testing

---

## Implementation Plan

### Phase 101: Convert KOption enum (1-2 hours)

**Files to modify**: 1 file
- `src/libraries/lstrlib.cpp`

**Steps**:
1. Convert enum definition to enum class
2. Update ~20 usage sites (case labels, assignments, comparisons)
3. Build and verify zero warnings
4. Run full test suite: `cd testes && ../build/lua all.lua`
5. Quick benchmark (3 runs) - expect no performance impact
6. Commit: "Phase 101: Convert KOption enum to enum class"

**Success Criteria**:
- ✅ Zero compilation warnings
- ✅ All tests pass ("final OK !!!")
- ✅ Performance ≤4.33s (no regression expected for library code)

---

### Phase 102: Convert expkind enum (2-3 hours)

**Files to modify**: 4 files
- `src/compiler/lparser.h` (definition)
- `src/compiler/parser.cpp` (main usage)
- `src/compiler/parseutils.cpp` (usage)
- `src/compiler/funcstate.cpp` (usage)

**Steps**:
1. Convert enum definition to enum class in `lparser.h`
2. Update expdesc class usage (field declarations unchanged)
3. Update parser.cpp usage sites (~15 locations)
4. Update parseutils.cpp usage sites (~5 locations)
5. Update funcstate.cpp usage sites (~2 locations)
6. Build and verify zero warnings
7. Run full test suite
8. Benchmark (5 runs) - minimal impact expected (compile-time only)
9. Commit: "Phase 102: Convert expkind enum to enum class"

**Success Criteria**:
- ✅ Zero compilation warnings
- ✅ All tests pass ("final OK !!!")
- ✅ Performance ≤4.33s (no regression expected for compiler code)

---

### Phase 103: Convert OpCode enum (3-4 hours)

**Files to modify**: 7 files (estimated)
- `src/compiler/lopcodes.h` (definition + utilities)
- `src/compiler/lopcodes.cpp` (implementation)
- `src/compiler/lcode.cpp` (heavy usage)
- `src/compiler/parser.cpp` (some usage)
- `src/vm/lvm.cpp` (VM interpreter - CRITICAL)
- `src/core/ldebug.cpp` (debug info)
- `src/testing/ltests.cpp` (testing)

**Steps**:
1. **Phase 103.1: Preparation**
   - Read and understand all current OpCode usage patterns
   - Identify all switch statements (must update case labels)
   - Identify all function parameters (type stays OpCode)
   - Identify all array indexing (needs static_cast<int>)

2. **Phase 103.2: Definition + Utilities**
   - Convert enum definition in `lopcodes.h`
   - Update `NUM_OPCODES` constant
   - Update utility functions in `lopcodes.h` and `lopcodes.cpp`
   - Build, verify compilation

3. **Phase 103.3: Code Generator**
   - Update `lcode.cpp` (~30+ sites)
   - Focus on function calls passing OpCode literals
   - Update any array/table indexing with OpCode
   - Build, verify compilation

4. **Phase 103.4: VM Interpreter** (MOST CRITICAL)
   - Update `lvm.cpp` switch statement (83 case labels)
   - Update any OpCode comparisons
   - Build, verify compilation
   - Run tests IMMEDIATELY after this step

5. **Phase 103.5: Parser + Debug**
   - Update `parser.cpp` usage (~5 sites)
   - Update `ldebug.cpp` usage (~5 sites)
   - Update `ltests.cpp` if needed
   - Build, verify zero warnings

6. **Phase 103.6: Testing**
   - Run full test suite (MANDATORY)
   - Verify "final OK !!!" output
   - Run 5-iteration benchmark
   - If performance > 4.33s, analyze and potentially revert

7. **Phase 103.7: Commit**
   - If all tests pass and performance acceptable:
   - Commit: "Phase 103: Convert OpCode enum to enum class"

**Success Criteria**:
- ✅ Zero compilation warnings
- ✅ All tests pass ("final OK !!!")
- ✅ Performance ≤4.33s (≤3% regression from 4.20s baseline)
- ✅ All 83 opcodes verified functional

**Rollback Plan**:
- If performance regression > 3%: Revert immediately
- If any test failures: Debug or revert
- Git allows easy rollback: `git reset --hard HEAD~1`

---

## Risk Mitigation

### General Safeguards

1. **Incremental Conversion**: One enum at a time, committed separately
2. **Build After Every File**: Catch compilation errors immediately
3. **Test After Every Phase**: Verify functionality before proceeding
4. **Benchmark After Significant Changes**: Especially Phase 103 (OpCode)
5. **Git Safety**: Clean commits allow easy rollback

### Performance Monitoring

**Baseline**: 4.20s avg (recent measurements)
**Target**: ≤4.33s (≤3% regression)
**Benchmark Command**:
```bash
cd testes
for i in 1 2 3 4 5; do \
    ../build/lua all.lua 2>&1 | grep "total time:"; \
done
```

**Expected Impact**:
- Phase 101 (KOption): No impact (library code, rarely called)
- Phase 102 (expkind): No impact (compile-time only)
- Phase 103 (OpCode): Potential impact (VM hot path, must verify)

### Compilation Verification

After each phase:
```bash
cd /home/user/lua_cpp
cmake --build build
# Must complete with ZERO warnings (-Werror active)
```

### Testing Protocol

After each phase:
```bash
cd testes
../build/lua all.lua
# Must output: "final OK !!!"
```

---

## Conversion Guidelines

### Pattern: Plain enum → enum class

**Before**:
```cpp
typedef enum {
  VALUE1,
  VALUE2,
  VALUE3
} EnumName;
```

**After**:
```cpp
enum class EnumName {
  VALUE1,
  VALUE2,
  VALUE3
};
```

### Pattern: Usage Updates

**Case Labels**:
```cpp
// Before
case VALUE1:
  ...
  break;

// After
case EnumName::VALUE1:
  ...
  break;
```

**Assignments**:
```cpp
// Before
EnumName var = VALUE1;

// After
EnumName var = EnumName::VALUE1;
```

**Comparisons**:
```cpp
// Before
if (var == VALUE1)

// After
if (var == EnumName::VALUE1)
```

**Array Indexing** (requires int):
```cpp
// Before
array[opcode]

// After
array[static_cast<int>(opcode)]
```

**Function Parameters** (type unchanged):
```cpp
// Before and After - NO CHANGE
void function(EnumName value) {
  ...
}
```

---

## Timeline Estimate

| Phase | Enum | Estimated Time | Risk Level |
|-------|------|----------------|------------|
| 101 | KOption | 1-2 hours | ⭐ LOW |
| 102 | expkind | 2-3 hours | ⭐⭐ MEDIUM |
| 103 | OpCode | 3-4 hours | ⭐⭐⭐ HIGH |
| **Total** | **All 3** | **6-9 hours** | - |

**Recommended Schedule**: Complete over 1-2 days with adequate testing breaks

---

## Success Metrics

### Completion Criteria

- ✅ All 3 enums converted to enum class
- ✅ Zero plain enums remaining in codebase
- ✅ Zero compilation warnings with -Werror
- ✅ All 30+ tests passing ("final OK !!!")
- ✅ Performance ≤4.33s (≤3% regression from 4.20s)
- ✅ Clean git history (3 commits, one per phase)

### Code Quality Improvements

- ✅ **Type Safety**: Enum class prevents implicit int conversions
- ✅ **Namespace Safety**: No name pollution from enum values
- ✅ **Modern C++**: Aligned with C++11/C++23 best practices
- ✅ **Consistency**: All enums now use enum class (19/19 completed)

### Documentation Updates

After completion, update `CLAUDE.md`:
- Change macro conversion status to: **100% of convertible enums complete**
- Update achievements section
- Document phases 101-103
- Final enum conversion milestone achieved

---

## Tools & Commands Reference

### Search for Remaining Enums
```bash
# Find plain enum definitions
grep -r "typedef enum" src/

# Find enum class definitions (already converted)
grep -r "enum class" src/
```

### Build Commands
```bash
cd /home/user/lua_cpp
cmake --build build
```

### Test Commands
```bash
cd testes
../build/lua all.lua
```

### Benchmark Commands
```bash
cd testes
for i in 1 2 3 4 5; do \
    ../build/lua all.lua 2>&1 | grep "total time:"; \
done
```

### Git Commands
```bash
git status
git add <files>
git commit -m "Phase N: Convert X enum to enum class"
git log --oneline -5
```

---

## Appendix: File Reference

### Files Requiring Changes

**Phase 101 (KOption)**:
- `src/libraries/lstrlib.cpp`

**Phase 102 (expkind)**:
- `src/compiler/lparser.h`
- `src/compiler/parser.cpp`
- `src/compiler/parseutils.cpp`
- `src/compiler/funcstate.cpp`

**Phase 103 (OpCode)**:
- `src/compiler/lopcodes.h`
- `src/compiler/lopcodes.cpp`
- `src/compiler/lcode.cpp`
- `src/compiler/parser.cpp`
- `src/vm/lvm.cpp` (CRITICAL)
- `src/core/ldebug.cpp`
- `src/testing/ltests.cpp`

### Total Impact
- **Files Modified**: ~11 files
- **Enums Converted**: 3
- **Estimated Total Changes**: ~150-200 sites
- **Estimated Total Time**: 6-9 hours

---

**Last Updated**: 2025-11-18
**Plan Status**: Ready for implementation
**Next Action**: Begin Phase 101 (KOption conversion)
